llm_ensemble/__init__.py
llm_ensemble/llm_models.py
llm_ensemble/llm_type.py
llm_ensemble/llms.py
llm_ensemble/shared.py
llm_ensemble/anthropic_llms/anthropic_llm_wrapper.py
llm_ensemble/anthropic_llms/anthropic_llms.py
llm_ensemble/openai_llms/openai_llm_wrapper.py
llm_ensemble/openai_llms/openai_models.py
llm_ensemble-0.0.2.dist-info/METADATA
llm_ensemble-0.0.2.dist-info/WHEEL
llm_ensemble-0.0.2.dist-info/licenses/LICENSE
llm_ensemble-0.0.2.dist-info/RECORD
